posixlake/__init__.py
posixlake/libposixlake.so
posixlake/posixlake.py
posixlake-0.1.5.dist-info/METADATA
posixlake-0.1.5.dist-info/WHEEL
posixlake-0.1.5.dist-info/top_level.txt
posixlake-0.1.5.dist-info/RECORD
