Metadata-Version: 2.1
Name: posixlake
Version: 0.1.5
Summary: High-performance Delta Lake database with POSIX interface and Python bindings
Home-page: https://github.com/npiesco/posixlake
Author: posixlake Contributors
Author-email: 
License: MIT
Project-URL: Bug Tracker, https://github.com/npiesco/posixlake/issues
Project-URL: Documentation, https://github.com/npiesco/posixlake#readme
Project-URL: Source Code, https://github.com/npiesco/posixlake
Keywords: database,delta-lake,sql,parquet,rust,datafusion,time-travel,acid,analytics
Classifier: Development Status :: 4 - Beta
Classifier: Intended Audience :: Developers
Classifier: License :: OSI Approved :: MIT License
Classifier: Programming Language :: Python :: 3
Classifier: Programming Language :: Python :: 3.8
Classifier: Programming Language :: Python :: 3.9
Classifier: Programming Language :: Python :: 3.10
Classifier: Programming Language :: Python :: 3.11
Classifier: Programming Language :: Python :: 3.12
Classifier: Programming Language :: Rust
Classifier: Topic :: Database
Classifier: Topic :: Software Development :: Libraries
Classifier: Operating System :: OS Independent
Requires-Python: >=3.8
